{
  "id": "modules/lesson_7/concept",
  "title": "Concept",
  "description": "Consumer Groups & Load Balancing - Scaling Kafka Consumers",
  "source": "@site/../class/modules/lesson_7/concept.md",
  "sourceDirName": "modules/lesson_7",
  "slug": "/modules/lesson_7/concept",
  "permalink": "/KafkaStarter/curriculum/modules/lesson_7/concept",
  "draft": false,
  "unlisted": false,
  "editUrl": "https://github.com/vorrawut/KafkaStarter/tree/main/class/../class/modules/lesson_7/concept.md",
  "tags": [],
  "version": "current",
  "frontMatter": {},
  "sidebar": "tutorialSidebar",
  "previous": {
    "title": "Workshop: Development Tools & Testing Framework",
    "permalink": "/KafkaStarter/curriculum/workshop/lesson_6/"
  },
  "next": {
    "title": "Workshop: Consumer Groups & Load Balancing",
    "permalink": "/KafkaStarter/curriculum/workshop/lesson_7/"
  }
}